artanis/__init__.py
artanis/client.py
artanis/trace.py
artanis/transport.py
artanis/types.py
artanis_ai-0.17.0.dist-info/METADATA
artanis_ai-0.17.0.dist-info/WHEEL
artanis_ai-0.17.0.dist-info/RECORD
